cdk_cloudformation_awsqs_kubernetes_get/__init__.py
cdk_cloudformation_awsqs_kubernetes_get/py.typed
cdk_cloudformation_awsqs_kubernetes_get/_jsii/__init__.py
cdk_cloudformation_awsqs_kubernetes_get/_jsii/awsqs-kubernetes-get@1.13.0-alpha.7.jsii.tgz
cdk_cloudformation_awsqs_kubernetes_get-1.13.0a7.dist-info/LICENSE
cdk_cloudformation_awsqs_kubernetes_get-1.13.0a7.dist-info/METADATA
cdk_cloudformation_awsqs_kubernetes_get-1.13.0a7.dist-info/WHEEL
cdk_cloudformation_awsqs_kubernetes_get-1.13.0a7.dist-info/top_level.txt
cdk_cloudformation_awsqs_kubernetes_get-1.13.0a7.dist-info/RECORD
